PyLibreHardwareMonitor/__init__.py
PyLibreHardwareMonitor/computer.py
PyLibreHardwareMonitor-1.2.2.dist-info/LICENSE
PyLibreHardwareMonitor-1.2.2.dist-info/METADATA
PyLibreHardwareMonitor-1.2.2.dist-info/WHEEL
PyLibreHardwareMonitor-1.2.2.dist-info/top_level.txt
PyLibreHardwareMonitor-1.2.2.dist-info/RECORD
