Metadata-Version: 2.1
Name: PyLibreHardwareMonitor
Version: 1.2.2
Summary: Python wrapper for LibreHardwareMonitor.
Author-email: jianjun <910667956@qq.com>
License: Mozilla Public License Version 2.0
Project-URL: homepage, https://github.com/EVA-JianJun/PyLibreHardwareMonitor
Project-URL: repository, https://github.com/EVA-JianJun/PyLibreHardwareMonitor
Requires-Python: >=3.6
License-File: LICENSE
Requires-Dist: rich
Requires-Dist: PyLibreHardwareMonitorLib
